openeo_gfmap/__init__.py
openeo_gfmap/backend.py
openeo_gfmap/metadata.py
openeo_gfmap/spatial.py
openeo_gfmap/temporal.py
openeo_gfmap/features/__init__.py
openeo_gfmap/features/feature_extractor.py
openeo_gfmap/fetching/__init__.py
openeo_gfmap/fetching/commons.py
openeo_gfmap/fetching/fetching.py
openeo_gfmap/fetching/generic.py
openeo_gfmap/fetching/s1.py
openeo_gfmap/fetching/s2.py
openeo_gfmap/inference/__init__.py
openeo_gfmap/inference/model_inference.py
openeo_gfmap/manager/__init__.py
openeo_gfmap/manager/job_manager.py
openeo_gfmap/manager/job_splitters.py
openeo_gfmap/preprocessing/__init__.py
openeo_gfmap/preprocessing/cloudmasking.py
openeo_gfmap/preprocessing/compositing.py
openeo_gfmap/preprocessing/interpolation.py
openeo_gfmap/preprocessing/sar.py
openeo_gfmap/preprocessing/scaling.py
openeo_gfmap/preprocessing/udf_cldmask.py
openeo_gfmap/preprocessing/udf_rank.py
openeo_gfmap/preprocessing/udf_score.py
openeo_gfmap/stac/__init__.py
openeo_gfmap/stac/constants.py
openeo_gfmap/utils/__init__.py
openeo_gfmap/utils/build_df.py
openeo_gfmap/utils/catalogue.py
openeo_gfmap/utils/intervals.py
openeo_gfmap/utils/netcdf.py
openeo_gfmap/utils/split_stac.py
openeo_gfmap/utils/tile_processing.py
openeo_gfmap-0.4.7.dist-info/METADATA
openeo_gfmap-0.4.7.dist-info/WHEEL
openeo_gfmap-0.4.7.dist-info/licenses/LICENSE
openeo_gfmap-0.4.7.dist-info/RECORD
