Metadata-Version: 2.4
Name: openeo_gfmap
Version: 0.4.7
Summary: OpenEO General Framework for Mapping
Project-URL: Homepage, https://github.com/Open-EO/openeo-gfmap
Project-URL: Bug Tracker, https://github.com/Open-EO/openeo-gfmap/issues
Author: Darius Couchard, Vincent Verelst, Kristof Van Tricht, Stefaan Lippens, Jeroen Degerickx
License-File: LICENSE
Classifier: Operating System :: OS Independent
Classifier: Programming Language :: Python :: 3
Requires-Python: >=3.8
Requires-Dist: cftime
Requires-Dist: fastparquet
Requires-Dist: geojson>=3.0.0
Requires-Dist: geopandas
Requires-Dist: h3==4.1.0
Requires-Dist: h5netcdf>=1.2.0
Requires-Dist: netcdf4
Requires-Dist: numpy<2.0.0
Requires-Dist: onnxruntime
Requires-Dist: openeo<=0.35
Requires-Dist: pyarrow
Requires-Dist: rasterio
Requires-Dist: s2sphere==0.2.*
Requires-Dist: scipy
Provides-Extra: dev
Requires-Dist: matplotlib>=3.3.0; extra == 'dev'
Requires-Dist: pre-commit; extra == 'dev'
Requires-Dist: pytest-depends; extra == 'dev'
Requires-Dist: pytest-timeout>=2.2.0; extra == 'dev'
Requires-Dist: pytest>=7.4.0; extra == 'dev'
Requires-Dist: requests-mock>=1.8.0; extra == 'dev'
Requires-Dist: rioxarray>=0.13.0; extra == 'dev'
Requires-Dist: xarray>=2022.3.0; extra == 'dev'
